Workbook

Sheet Premissas
A1: BLESSED | Premissas editáveis
A2: Azul-claro = valor editável. Todos os cenários são hipóteses, não previsão nem resultado atual.
A4: Premissa | B4: Valor | C4: Unidade / condição | D4: Origem
A5: Câmbio de planejamento | B5: 6 | C5: R$/US$ — não é cotação | D5: Hipótese
A6: Assinatura pessoal | B6: 14.9 | C6: R$/mês | D6: Oferta exibida no app
A7: Assinatura empresa | B7: 34.9 | C7: R$/mês | D7: Oferta exibida no app
A8: Conversão pessoal | B8: 0.02 | C8: Fração dos ativos mensais | D8: Hipótese
A9: Conversão empresa | B9: 0.002 | C9: Fração dos ativos mensais | D9: Hipótese
A10: Reserva de deduções | B10: 0.12 | C10: Taxas / tributos / reembolsos | D10: Hipótese; validar com contador
A11: Custo fixo total do exemplo | B11: 8000 | C11: Inclui infraestrutura e operação | D11: Hipótese
A12: R2 por GB-mês | B12: 0.015 | C12: US$; Standard | D12: Cloudflare R2
A13: Franquia R2 | B13: 10 | C13: GB-mês; Standard | D13: Cloudflare R2
A14: Supabase Pro mínimo | B14: 25 | C14: US$/mês; um projeto Micro | D14: Supabase oficial
A15: Workers pago opcional | B15: 5 | C15: US$/mês; mínimo | D15: Cloudflare Workers

Sheet Receita
A1: BLESSED | Cenários de receita
A2: Receita recorrente hipotética. Não inclui Cine, campanhas, anúncios, lucro ou fatura real.
A4: Ativos/mês | B4: Pessoas pagantes | C4: Empresas pagantes | D4: Receita bruta R$ | E4: Após deduções R$ | F4: Conversão total
A5: 1000 | B5: =ROUNDDOWN(A5*Premissas!$B$8,0) -> 20 | C5: =ROUNDDOWN(A5*Premissas!$B$9,0) -> 2 | D5: =B5*Premissas!$B$6+C5*Premissas!$B$7 -> 367.8 | E5: =D5*(1-Premissas!$B$10) -> 323.664 | F5: =(B5+C5)/A5 -> 0.022
A6: 10000 | B6: =ROUNDDOWN(A6*Premissas!$B$8,0) -> 200 | C6: =ROUNDDOWN(A6*Premissas!$B$9,0) -> 20 | D6: =B6*Premissas!$B$6+C6*Premissas!$B$7 -> 3678 | E6: =D6*(1-Premissas!$B$10) -> 3236.64 | F6: =(B6+C6)/A6 -> 0.022
A7: 100000 | B7: =ROUNDDOWN(A7*Premissas!$B$8,0) -> 2000 | C7: =ROUNDDOWN(A7*Premissas!$B$9,0) -> 200 | D7: =B7*Premissas!$B$6+C7*Premissas!$B$7 -> 36780 | E7: =D7*(1-Premissas!$B$10) -> 32366.4 | F7: =(B7+C7)/A7 -> 0.022

Sheet Infraestrutura
A1: BLESSED | Exemplo de manutenção técnica
A2: Exemplo de base leve. Orçamento de serviço não é fatura atual. Câmbio, cotas e reservas são editáveis.
A4: Item | B4: Unidade / base | C4: Custo US$/mês | D4: Custo R$/mês | E4: Classificação
A5: Supabase Pro | B5: 1 projeto | C5: =Premissas!B14 -> 25 | D5: =C5*Premissas!$B$5 -> 150 | E5: Referência oficial
A6: R2 Standard · 100 GB | B6: 100 GB mantidos no mês | C6: =MAX(0,100-Premissas!$B$13)*Premissas!$B$12 -> 1.35 | D6: =C6*Premissas!$B$5 -> 8.1 | E6: Só armazenamento
A7: Workers pago opcional | B7: Plano mínimo | C7: =Premissas!B15 -> 5 | D7: =C7*Premissas!$B$5 -> 30 | E7: Alternativa a avaliar
A8: Domínio | B8: Provisão mensal | D8: 5 | E8: Orçamento
A9: E-mail transacional | B9: Reserva mensal | D9: 80 | E9: Orçamento
A10: Monitoramento | B10: Reserva mensal | D10: 60 | E10: Orçamento
A11: Backup / segurança | B11: Reserva mensal | D11: 60 | E11: Orçamento
A12: Processamento de mídia | B12: Reserva mensal | D12: 100 | E12: Orçamento
A14: TOTAL TÉCNICO DO EXEMPLO | D14: =SUM(D5:D12) -> 493.1
A16: Fora do total: equipe, moderação, marketing, jurídico, taxas de pagamento e tributos. Operações do R2 e usos excedentes não estão calculados neste exemplo. As faixas do PDF são envelopes de planejamento mais amplos.

Sheet Equilibrio
A1: BLESSED | Equilíbrio ilustrativo
A2: Não é previsão. O custo fixo abaixo já deve conter o orçamento técnico para evitar dupla contagem.
A4: Indicador | B4: Valor | C4: Interpretação
A5: Custo fixo total R$/mês | B5: =Premissas!B11 -> 8000 | C5: Infraestrutura + pessoas + operação
A6: Receita bruta do cenário de 10 mil | B6: =Receita!D6 -> 3678 | C6: 200 pessoais + 20 empresas
A7: Pagantes do cenário | B7: =SUM(Receita!B6:C6) -> 220 | C7: Assinaturas hipotéticas
A8: Ticket médio R$/assinante | B8: =B6/B7 -> 16.718182 | C8: Receita bruta dividida por pagantes
A9: Contribuição R$/assinante | B9: =B8*(1-Premissas!B10) -> 14.712 | C9: Após reserva ilustrativa de 12%
A10: Pagantes para cobrir custo fixo | B10: =ROUNDUP(B5/B9,0) -> 544 | C10: Arredondado para cima
A11: Conversão necessária em 10 mil | B11: =B10/10000 -> 0.0544 | C11: Pagantes divididos por ativos

Sheet Fontes
A1: BLESSED | Fontes
A2: Preços consultados em 22/10/2026. Confirmar condições comerciais e faturas antes da contratação.
A4: Fonte | B4: Endereço / evidência
A5: Supabase planos | B5: https://github.com/supabase/supabase/blob/master/packages/shared-data/plans.ts
A6: Supabase uso | B6: https://github.com/supabase/supabase/blob/master/packages/shared-data/pricing.ts
A7: Cloudflare R2 | B7: https://developers.cloudflare.com/r2/pricing/
A8: Cloudflare Workers | B8: https://developers.cloudflare.com/workers/platform/pricing/
A9: Preços ao usuário | B9: App Blessed, revisão bb28636, funções vfPrice e cnDetail
A10: Câmbio / conversão / deduções | B10: Hipóteses gerenciais; não foram usados como dados históricos
